elematic/__init__.py
elematic/ds.py
elematic/util.py
elematic-2.0.0.dist-info/LICENSE
elematic-2.0.0.dist-info/METADATA
elematic-2.0.0.dist-info/WHEEL
elematic-2.0.0.dist-info/RECORD
