Metadata-Version: 2.3
Name: elematic
Version: 2.0.0
Summary: Materials information management via MatML for Python
License: MIT License
Author: Noah Gula
Requires-Python: >=3.10,<3.14
Classifier: License :: Other/Proprietary License
Classifier: Programming Language :: Python :: 3
Classifier: Programming Language :: Python :: 3.10
Classifier: Programming Language :: Python :: 3.11
Classifier: Programming Language :: Python :: 3.12
Classifier: Programming Language :: Python :: 3.13
Requires-Dist: lxml (>=5.3.0,<6.0.0)
Requires-Dist: pyside6-essentials (>=6.8.2.1,<7.0.0.0)
Requires-Dist: xsdata-pydantic[cli,lxml,soap] (>=24.5,<25.0)
Requires-Dist: xsdata[cli] (>=24.12,<25.0)
Project-URL: Documentation, https://github.com/nogula/elematic/wiki
Project-URL: Homepage, https://github.com/nogula/elematic
Project-URL: Issues, https://github.com/nogula/elematic/issues
Project-URL: Repository, https://github.com/nogula/elematic
